sgcalculator
sgcalculator/src
sgcalculator/test
