Metadata-Version: 1.0
Name: sgcalculator
Version: 0.13
Summary:  Simple analytics module for looking at population data.
Home-page: https://bitbucket.org/renford/sgcalculator
Author: Renford Alexander
Author-email: alexander.Renford@gmail.com
License: MIT
Platform: UNKNOWN
